odoo10_addon_mail_full_expand-10.0.1.0.1-py3.8-nspkg.pth
odoo/addons/mail_full_expand/README.rst
odoo/addons/mail_full_expand/__init__.py
odoo/addons/mail_full_expand/__manifest__.py
odoo/addons/mail_full_expand/i18n/ca.po
odoo/addons/mail_full_expand/i18n/de.po
odoo/addons/mail_full_expand/i18n/es.po
odoo/addons/mail_full_expand/i18n/es_CO.po
odoo/addons/mail_full_expand/i18n/fr.po
odoo/addons/mail_full_expand/i18n/hr.po
odoo/addons/mail_full_expand/i18n/it.po
odoo/addons/mail_full_expand/i18n/mail_full_expand.pot
odoo/addons/mail_full_expand/i18n/nb.po
odoo/addons/mail_full_expand/i18n/nl.po
odoo/addons/mail_full_expand/i18n/nl_NL.po
odoo/addons/mail_full_expand/i18n/pt.po
odoo/addons/mail_full_expand/i18n/pt_BR.po
odoo/addons/mail_full_expand/i18n/sl.po
odoo/addons/mail_full_expand/i18n/tr.po
odoo/addons/mail_full_expand/i18n/tr_TR.po
odoo/addons/mail_full_expand/static/description/icon.png
odoo/addons/mail_full_expand/static/src/css/mail_full_expand.less
odoo/addons/mail_full_expand/static/src/js/mail_full_expand.js
odoo/addons/mail_full_expand/static/src/xml/mail_full_expand.xml
odoo/addons/mail_full_expand/views/assets.xml
odoo/addons/mail_full_expand/views/mail_full_expand.xml
odoo10_addon_mail_full_expand-10.0.1.0.1.dist-info/METADATA
odoo10_addon_mail_full_expand-10.0.1.0.1.dist-info/WHEEL
odoo10_addon_mail_full_expand-10.0.1.0.1.dist-info/namespace_packages.txt
odoo10_addon_mail_full_expand-10.0.1.0.1.dist-info/top_level.txt
odoo10_addon_mail_full_expand-10.0.1.0.1.dist-info/RECORD
